terra_classic_sdk/.DS_Store
terra_classic_sdk/__init__.py
terra_classic_sdk/client/__init__.py
terra_classic_sdk/client/lcd/__init__.py
terra_classic_sdk/client/lcd/api/__init__.py
terra_classic_sdk/client/lcd/api/_base.py
terra_classic_sdk/client/lcd/api/auth.py
terra_classic_sdk/client/lcd/api/authz.py
terra_classic_sdk/client/lcd/api/bank.py
terra_classic_sdk/client/lcd/api/distribution.py
terra_classic_sdk/client/lcd/api/feegrant.py
terra_classic_sdk/client/lcd/api/gov.py
terra_classic_sdk/client/lcd/api/ibc.py
terra_classic_sdk/client/lcd/api/ibc_transfer.py
terra_classic_sdk/client/lcd/api/market.py
terra_classic_sdk/client/lcd/api/mint.py
terra_classic_sdk/client/lcd/api/oracle.py
terra_classic_sdk/client/lcd/api/pool.py
terra_classic_sdk/client/lcd/api/slashing.py
terra_classic_sdk/client/lcd/api/staking.py
terra_classic_sdk/client/lcd/api/tendermint.py
terra_classic_sdk/client/lcd/api/treasury.py
terra_classic_sdk/client/lcd/api/tx.py
terra_classic_sdk/client/lcd/api/wasm.py
terra_classic_sdk/client/lcd/lcdclient.py
terra_classic_sdk/client/lcd/lcdutils.py
terra_classic_sdk/client/lcd/params.py
terra_classic_sdk/client/lcd/wallet.py
terra_classic_sdk/client/localterra.py
terra_classic_sdk/core/.DS_Store
terra_classic_sdk/core/__init__.py
terra_classic_sdk/core/auth/__init__.py
terra_classic_sdk/core/auth/data/__init__.py
terra_classic_sdk/core/auth/data/account.py
terra_classic_sdk/core/auth/data/base_account.py
terra_classic_sdk/core/auth/data/base_vesting_account.py
terra_classic_sdk/core/auth/data/lazy_graded_vesting_account.py
terra_classic_sdk/core/authz/__init__.py
terra_classic_sdk/core/authz/data.py
terra_classic_sdk/core/authz/msgs.py
terra_classic_sdk/core/bank/__init__.py
terra_classic_sdk/core/bank/msgs.py
terra_classic_sdk/core/bech32.py
terra_classic_sdk/core/block.py
terra_classic_sdk/core/broadcast.py
terra_classic_sdk/core/coin.py
terra_classic_sdk/core/coins.py
terra_classic_sdk/core/compact_bit_array.py
terra_classic_sdk-3.0.2.dist-info/LICENSE
terra_classic_sdk-3.0.2.dist-info/METADATA
terra_classic_sdk-3.0.2.dist-info/WHEEL
terra_classic_sdk-3.0.2.dist-info/RECORD
